{
  "extension.config.title": "Dev Toolbox",
  "extension.config.encoding.doubleEncode.desc": "Zaten kaçış uygulanmış dizilerin yeniden kodlanmasını açıp kapatır. Kapalıyken kodlayıcılar ürettikleri mevcut kaçışları olduğu gibi bırakır. Tüm kodlayıcılara uygulanır. Varsayılan: kapalı.",
  "extension.config.slugify.desc": "Slug’a dönüştürülmüş metinde ayırıcı olarak kullanılan karakter.",
  "extension.config.slugify.dash.desc": "Ayraç olarak kısa çizgi (-) kullan",
  "extension.config.slugify.underscore.desc": "Ayraç olarak alt çizgi (_) kullan",
  "extension.config.uuid.desc": "Oluşturulan UUID/GUID biçimi.",
  "extension.config.uuid.raw.desc": "Ham biçim xxxxxxxx-xxxx-xxxx-xxxx-xxxxxxxxxxxx",
  "extension.config.uuid.registryFormat.desc": "Kayıt defteri biçimi {xxxxxxxx-xxxx-xxxx-xxxx-xxxxxxxxxxxx}",
  "extension.config.uuid.squareFormat.desc": "Köşeli ayraç biçimi [Guid(\"xxxxxxxx-xxxx-xxxx-xxxx-xxxxxxxxxxxx\")]",
  "extension.config.uuid.lessThanSignFormat.desc": "Açılı ayraç biçimi <Guid(\"xxxxxxxx-xxxx-xxxx-xxxx-xxxxxxxxxxxx\")>",
  "extension.config.removeEmptyLines.considerWhitespaceEmpty.desc": "Değer true ise yalnızca boşluk karakterleri (boşluk, sekme) içeren satırlar boş sayılır. Değer false ise yalnızca tamamen boş satırlar kaldırılır.",
  "extension.command.reportIssue.title": "Sorun bildir",
  "extension.command.slugify.title": "URL slugu oluştur",
  "extension.command.slugifyFileOrFolder.title": "URL sluga dönüştür",
  "extension.command.toCamelCase.title": "camelCase’e dönüştür (myVariableName)",
  "extension.command.toPascalCase.title": "PascalCase’e dönüştür (MyClassName)",
  "extension.command.toSnakeCase.title": "snake_case’e dönüştür (my_variable_name)",
  "extension.command.toScreamingSnakeCase.title": "SCREAMING_SNAKE_CASE’e dönüştür (MY_CONSTANT_NAME)",
  "extension.command.toKebabCase.title": "kebab-case’e dönüştür (my-variable-name)",
  "extension.command.toTrainCase.title": "TRAIN-CASE’e dönüştür (MY-VARIABLE-NAME)",
  "extension.command.toFlatCase.title": "flatcase’e dönüştür (myvariablename)",
  "extension.command.toUpperCase.title": "UPPERCASE’e dönüştür (MYVARIABLENAME)",
  "extension.command.makeLowercase.title": "lowercase’e dönüştür (myvariablename)",
  "extension.command.makeUppercase.title": "UPPERCASE’e dönüştür (MYVARIABLENAME)",
  "extension.command.base64Encode.title": "Base64 kodla",
  "extension.command.base64Decode.title": "Base64 çöz",
  "extension.command.urlEncode.title": "URL kodla",
  "extension.command.urlDecode.title": "URL çöz",
  "extension.command.generateGuid.title": "UUID/GUID üret",
  "extension.command.removeEmptyLinesDocument.title": "Belgeden boş satırları kaldır",
  "extension.command.removeEmptyLinesSelection.title": "Seçimden boş satırları kaldır",
  "extension.command.removeNonPrintableChars.title": "Yazdırılamayan karakterleri kaldır",
  "extension.command.removeLeadingTrailingWhitespace.title": "Baş ve sondaki boşlukları kaldır",
  "extension.command.encodeNamedHtmlEntities.title": "Adlandırılmış HTML varlıklarını kodla (&amp;, &quot;)",
  "extension.command.decodeNamedHtmlEntities.title": "Adlandırılmış HTML varlıklarının kodunu çöz (&amp;, &quot;)",
  "extension.command.encodeHtmlHexEntities.title": "Onaltılık HTML varlıklarını kodla (&#x0012;)",
  "extension.command.decodeHtmlHexEntities.title": "Onaltılık HTML varlıklarının kodunu çöz (&#x0012;)",
  "extension.command.encodeHtmlDecimalEntities.title": "Ondalık HTML varlıklarını kodла (&#123;)",
  "extension.command.decodeHtmlDecimalEntities.title": "Ondalık HTML varlıklarının kodunu çöz (&#123;)",
  "extension.command.encodeJavaScriptUTF16EscapeSequences.title": "JavaScript UTF-16 kaçış dizilerini kodla (\\UXXXXXXXX, \\uXXXX)",
  "extension.command.decodeJavaScriptUTF16EscapeSequences.title": "JavaScript UTF-16 kaçış dizilerinin kodunu çöz (\\UXXXXXXXX, \\uXXXX)",
  "extension.command.encodeCssUnicodeEscape.title": "CSS Unicode kaçış dizilerini kodла (\\XXXXXX)",
  "extension.command.decodeCssUnicodeEscape.title": "CSS Unicode kaçış dizilerinin kodunu çöz (\\XXXXXX)",
  "extension.command.encodeUnicodeCodePointNotation.title": "Unicode kod noktası gösterimini kodla (U+XXXX)",
  "extension.command.decodeUnicodeCodePointNotation.title": "Unicode kod noktası gösteriminin kodunu çöz (U+XXXX)",
  "extension.command.encodeUnicodeCodePointEscapeSequence.title": "Unicode kod noktası kaçış dizisini kodla (\\u{XXXXXX})",
  "extension.command.decodeUnicodeCodePointEscapeSequence.title": "Unicode kod noktası kaçış dizisini çöz (\\u{XXXXXX})",
  "extension.command.encodeHexEntities.title": "Genişletilmiş onaltılık kaçış dizilerini kodла (\\x{XXXXXX})",
  "extension.command.decodeHexEntities.title": "Genişletilmiş onaltılık kaçış dizilerinin kodunu çöz (\\x{XXXXXX})",
  "extension.command.encodeHexCodePoints.title": "Onaltılık kod noktalarını kodла (0xXXXX)",
  "extension.command.decodeHexCodePoints.title": "Onaltılık kod noktalarının kodunu çöz (0xXXXX)"
}